{
  "bundle_id": "managed-local",
  "release_version": "0.5.7",
  "version": "0.5.7",
  "channel": "stable",
  "digest": "sha256:0e47c29aaca52179b20a8169f56d2f9990fb658ca59890f0becfb86d551472dc",
  "signature": {
    "scheme": "ed25519-sha256-v1",
    "key_id": "spidervenoms-dev-2026-03",
    "value": "gYZiowUj5FhjV/qmXLRhUIP4ctWXAJPXKRe9OSSrLKLXYfIpLWZBvgl6eZfBRkdZf/GLMyjvBLhl9H48gxwdCQ=="
  },
  "trust": {
    "mode": "signed",
    "publisher": "SpiderVenoms",
    "allow_dev_unsigned": false
  },
  "executables": [
    {
      "id": "local-service",
      "source": {
        "kind": "bundle_relative",
        "path": "bin/spiderweb-local-service"
      },
      "stage_path": "bin/spiderweb-local-service"
    },
    {
      "id": "computer-driver",
      "source": {
        "kind": "bundle_relative",
        "path": "bin/spiderweb-computer-driver"
      },
      "stage_path": "bin/spiderweb-computer-driver",
      "platforms": [
        "macos"
      ]
    },
    {
      "id": "browser-driver",
      "source": {
        "kind": "bundle_relative",
        "path": "bin/spiderweb-browser-driver"
      },
      "stage_path": "bin/spiderweb-browser-driver",
      "platforms": [
        "macos"
      ]
    }
  ],
  "packages": [
    {
      "package_id": "terminal",
      "venom_id": "terminal",
      "kind": "terminal",
      "release_version": "0.5.7",
      "version": "0.5.7",
      "channel": "stable",
      "digest": "sha256:433b77d38d0e13d601b3483d41b5a388d177f424be4162d635faee01e91f68ff",
      "signature": {
        "scheme": "ed25519-sha256-v1",
        "key_id": "spidervenoms-dev-2026-03",
        "value": "lL4ukd4lUW7f3ae50Q3s4PBVynnHx9FFe4++HNwTHn+RAJWJoZb/1gMwWLCNX6ud8FhCThnYiWbfvHBrw7dVDg=="
      },
      "trust": {
        "mode": "signed",
        "publisher": "SpiderVenoms",
        "allow_dev_unsigned": false
      },
      "manifest_path": "manifests/terminal.json",
      "executable_id": "local-service",
      "template_bindings": {
        "__EXPORT_ROOT__": {
          "kind": "export_root"
        }
      }
    },
    {
      "package_id": "git",
      "venom_id": "git",
      "kind": "git",
      "release_version": "0.5.7",
      "version": "0.5.7",
      "channel": "stable",
      "digest": "sha256:756341446def2724ce29ca4a14f88c5d0dc237e9e891678bf6fa15f5853c5f7e",
      "signature": {
        "scheme": "ed25519-sha256-v1",
        "key_id": "spidervenoms-dev-2026-03",
        "value": "/EGf0l/DwudxjPZ6qeh7/mfNBa1cQkMqD7rkqbt5LrBXm0OUwo8CnM6hYuQ5+xuRf0euThe2FniAdqI5c4k0CA=="
      },
      "trust": {
        "mode": "signed",
        "publisher": "SpiderVenoms",
        "allow_dev_unsigned": false
      },
      "manifest_path": "manifests/git.json",
      "executable_id": "local-service",
      "template_bindings": {
        "__EXPORT_ROOT__": {
          "kind": "export_root"
        }
      }
    },
    {
      "package_id": "search_code",
      "venom_id": "search_code",
      "kind": "search_code",
      "release_version": "0.5.7",
      "version": "0.5.7",
      "channel": "stable",
      "digest": "sha256:60bced0c260da0d0f6a15e2173a84d32078a9b7d7ef61330fce39c031adedb12",
      "signature": {
        "scheme": "ed25519-sha256-v1",
        "key_id": "spidervenoms-dev-2026-03",
        "value": "9IdT5kJYYjMaPUDZchDNNF9KebOCXmgh9hslRUCOthldSnUNFMuC3uFD2rMEjdWExXv87/Dtvhdtj3kztv7KDA=="
      },
      "trust": {
        "mode": "signed",
        "publisher": "SpiderVenoms",
        "allow_dev_unsigned": false
      },
      "manifest_path": "manifests/search_code.json",
      "executable_id": "local-service",
      "template_bindings": {
        "__EXPORT_ROOT__": {
          "kind": "export_root"
        }
      }
    },
    {
      "package_id": "computer",
      "venom_id": "computer-main",
      "kind": "computer",
      "release_version": "0.5.7",
      "version": "0.5.7",
      "channel": "stable",
      "digest": "sha256:4d5d938bc400a26a45b172ad144df683d2fc593502b8376470da4bb493d64e72",
      "signature": {
        "scheme": "ed25519-sha256-v1",
        "key_id": "spidervenoms-dev-2026-03",
        "value": "zv7+VfXYCteYlPVk0+73itnJ6sTeNCI1JRsq1lTg3yKZv13dcN3DIMjlF6VpScqFT0Vu/AcZC/U7MJ5hXon8Aw=="
      },
      "trust": {
        "mode": "signed",
        "publisher": "SpiderVenoms",
        "allow_dev_unsigned": false
      },
      "manifest_path": "manifests/computer.json",
      "executable_id": "computer-driver"
    },
    {
      "package_id": "browser",
      "venom_id": "browser-main",
      "kind": "browser",
      "release_version": "0.5.7",
      "version": "0.5.7",
      "channel": "stable",
      "digest": "sha256:182e34c10c24fa2b8f1f34385e4a06809367d7fef57ae38c4057b640804d42b3",
      "signature": {
        "scheme": "ed25519-sha256-v1",
        "key_id": "spidervenoms-dev-2026-03",
        "value": "hDAUDKHt4fDDploTIe80pfA6fn6JFnv658mcL1VJDTbcdgM4Zhj3dM88J6OpyRZaFfYx6bR0Pdaj9IExt4ljAg=="
      },
      "trust": {
        "mode": "signed",
        "publisher": "SpiderVenoms",
        "allow_dev_unsigned": false
      },
      "manifest_path": "manifests/browser.json",
      "executable_id": "browser-driver",
      "template_bindings": {
        "__STATE_PATH__": {
          "kind": "state_file",
          "path": "browser/state.json"
        },
        "__PROFILE_DIR__": {
          "kind": "state_dir",
          "path": "browser/profile"
        }
      }
    }
  ]
}
